tests/__init__.py
tests/ptest_parser.py
tests/test_module_checksum_image.py
tests/test_module_compare_tiffs.py
tests/test_module_rgb72_migration.py
tifinity/__init__.py
tifinity/__main__.py
tifinity/actions/__init__.py
tifinity/actions/checksum.py
tifinity/actions/icc_parser.py
tifinity/actions/rgb72_to_rgb96.py
tifinity/modules/__init__.py
tifinity/modules/checksum_image.py
tifinity/modules/compare_tiffs.py
tifinity/modules/rgb72_migration.py
tifinity/modules/tiff_details.py
tifinity/parser/__init__.py
tifinity/parser/errors.py
tifinity/parser/tiff.py
tifinity/scripts/__init__.py
tifinity/scripts/icc_check.py
tifinity/scripts/perceptual_eval.py
tifinity/scripts/timing.py
tifinity-0.3.0.dist-info/METADATA
tifinity-0.3.0.dist-info/RECORD
tifinity-0.3.0.dist-info/WHEEL
tifinity-0.3.0.dist-info/entry_points.txt
tifinity-0.3.0.dist-info/top_level.txt
