Metadata-Version: 2.1
Name: tifinity
Version: 0.3.0
Summary: Framework and helpful utilities for working with TIFFs
Home-page: https://github.com/pmay/tifinity
Author: Peter May
Author-email: Peter.May@bl.uk
License: Apache Licence 2.0
Platform: UNKNOWN
Classifier: Development Status :: 2 - Pre-Alpha
Classifier: Intended Audience :: End Users/Desktop
Classifier: Topic :: Utilities
Classifier: Topic :: Multimedia :: Graphics :: Graphics Conversion
Classifier: License :: OSI Approved :: Apache Software License
Classifier: Programming Language :: Python :: 3.6
Requires-Dist: numpy (>=1.13.3)
